arlogi/__init__.py
arlogi/config.py
arlogi/config_builder.py
arlogi/factory.py
arlogi/handler_factory.py
arlogi/handlers.py
arlogi/levels.py
arlogi/py.typed
arlogi/types.py
arlogi-0.601.4.dist-info/METADATA
arlogi-0.601.4.dist-info/WHEEL
arlogi-0.601.4.dist-info/licenses/LICENSE
arlogi-0.601.4.dist-info/RECORD
