Metadata-Version: 2.4
Name: arlogi
Version: 0.601.4
Summary: Robust, type-safe and highly configurable logging library for Python
Author-email: Anton Razumov <arazumov@checkpoint.com>
License-File: LICENSE
Requires-Python: >=3.13
Requires-Dist: rich>=14.2.0
